montmark/__init__.py
montmark/__main__.py
montmark/montmark.py
montmark-0.0.1.dist-info/licenses/LICENSE
montmark-0.0.1.dist-info/METADATA
montmark-0.0.1.dist-info/WHEEL
montmark-0.0.1.dist-info/top_level.txt
montmark-0.0.1.dist-info/RECORD
